keyedarchivelib/__init__.py
keyedarchivelib/api.py
keyedarchivelib/compat.py
keyedarchivelib/py.typed
keyedarchivelib/util.py
keyedarchivelib-1.0.2.dist-info/LICENSE.txt
keyedarchivelib-1.0.2.dist-info/METADATA
keyedarchivelib-1.0.2.dist-info/WHEEL
keyedarchivelib-1.0.2.dist-info/top_level.txt
keyedarchivelib-1.0.2.dist-info/RECORD
