Metadata-Version: 2.1
Name: keyedarchivelib
Version: 1.0.2
Summary: Generate and parse NSKeyedArchive files
Home-page: https://github.com/bigfootjon/keyedarchivelib
Author: Jonathan Janzen
Author-email: jjjonjanzen@gmail.com
License: GNU Lesser General Public License v3 (LGPLv3)
Download-URL: https://github.com/bigfootjon/keyedarchivelib/tarball/1.0.2
Platform: UNKNOWN
Classifier: Development Status :: 5 - Production/Stable
Classifier: Operating System :: OS Independent
Classifier: Intended Audience :: Developers
Classifier: License :: OSI Approved :: GNU Lesser General Public License v3 (LGPLv3)
Classifier: Natural Language :: English
Classifier: Programming Language :: Python
Classifier: Programming Language :: Python :: 3.6
Classifier: Programming Language :: Python :: 3.7
Classifier: Programming Language :: Python :: 3.8
Classifier: Programming Language :: Python :: 3.9
Classifier: Programming Language :: Python :: 3.10
Classifier: Programming Language :: Python :: 3 :: Only
Classifier: Typing :: Typed
Requires-Python: >=3.6
